{
    "Ar36": {
        "error": 0.0006793940828445889,
        "error_type": "SEM",
        "filter_outliers_dict": {
            "filter_outliers": true,
            "iterations": 1,
            "std_devs": 2
        },
        "fit": "linear",
        "value": 0.03260136707095772
    },
    "Ar37": {
        "error": 0.008177186768197434,
        "error_type": "SEM",
        "filter_outliers_dict": {
            "filter_outliers": true,
            "iterations": 1,
            "std_devs": 2
        },
        "fit": "linear",
        "value": 0.0022066171568026894
    },
    "Ar38": {
        "error": 0.007472704133704782,
        "error_type": "SEM",
        "filter_outliers_dict": {
            "filter_outliers": true,
            "iterations": 1,
            "std_devs": 2
        },
        "fit": "linear",
        "value": 0.34137492172238815
    },
    "Ar39": {
        "error": 0.03903150545661981,
        "error_type": "SEM",
        "filter_outliers_dict": {
            "filter_outliers": true,
            "iterations": 1,
            "std_devs": 2
        },
        "fit": "parabolic",
        "value": 21.56771573496488
    },
    "Ar40": {
        "error": 0.08941941362704008,
        "error_type": "SEM",
        "filter_outliers_dict": {
            "filter_outliers": true,
            "iterations": 1,
            "std_devs": 3
        },
        "fit": "parabolic",
        "value": 183.24796203656194
    },
    "Ar41": {
        "error": 0.031104572411132313,
        "error_type": "SEM",
        "filter_outliers_dict": {
            "filter_outliers": true,
            "iterations": 1,
            "std_devs": 3
        },
        "fit": "average",
        "value": -0.1462083855411702
    }
}